chuangliang/__init__.py
chuangliang/crawler.py
chuangliang/open_api.py
chuangliang-0.0.17.dist-info/LICENSE
chuangliang-0.0.17.dist-info/METADATA
chuangliang-0.0.17.dist-info/WHEEL
chuangliang-0.0.17.dist-info/top_level.txt
chuangliang-0.0.17.dist-info/RECORD
