Metadata-Version: 2.1
Name: chuangliang
Version: 0.0.17
Summary: 创量广告平台SDK
Home-page: https://gitee.com/ZeroSeeker/chuangliang
Author: ZeroSeeker
Author-email: zeroseeker@foxmail.com
Classifier: Programming Language :: Python :: 3
Classifier: License :: OSI Approved :: MIT License
Classifier: Operating System :: OS Independent
License-File: LICENSE
Requires-Dist: lazysdk>=0.1.89
